openprotein/__init__.py
openprotein/_version.py
openprotein/base.py
openprotein/chains.py
openprotein/config.py
openprotein/csv.py
openprotein/errors.py
openprotein/fasta.py
openprotein/protein.py
openprotein/scaffolds.py
openprotein/align/__init__.py
openprotein/align/align.py
openprotein/align/api.py
openprotein/align/future.py
openprotein/align/msa.py
openprotein/align/schemas.py
openprotein/api/__init__.py
openprotein/api/align.py
openprotein/api/assaydata.py
openprotein/api/design.py
openprotein/api/designer.py
openprotein/api/embedding.py
openprotein/api/error.py
openprotein/api/fold.py
openprotein/api/job.py
openprotein/api/predict.py
openprotein/api/predictor.py
openprotein/api/prompt.py
openprotein/api/svd.py
openprotein/api/train.py
openprotein/api/umap.py
openprotein/api/deprecated/__init__.py
openprotein/api/deprecated/design.py
openprotein/api/deprecated/poet.py
openprotein/api/deprecated/predict.py
openprotein/api/deprecated/train.py
openprotein/app/__init__.py
openprotein/app/deprecated.py
openprotein/app/models/__init__.py
openprotein/app/models/assaydata.py
openprotein/app/models/design.py
openprotein/app/models/designer.py
openprotein/app/models/futures.py
openprotein/app/models/predict.py
openprotein/app/models/prompt.py
openprotein/app/models/svd.py
openprotein/app/models/train.py
openprotein/app/models/umap.py
openprotein/app/models/align/__init__.py
openprotein/app/models/align/base.py
openprotein/app/models/align/msa.py
openprotein/app/models/align/prompt.py
openprotein/app/models/deprecated/__init__.py
openprotein/app/models/deprecated/design.py
openprotein/app/models/deprecated/poet.py
openprotein/app/models/deprecated/predict.py
openprotein/app/models/deprecated/train.py
openprotein/app/models/embeddings/__init__.py
openprotein/app/models/embeddings/base.py
openprotein/app/models/embeddings/esm.py
openprotein/app/models/embeddings/future.py
openprotein/app/models/embeddings/openprotein.py
openprotein/app/models/embeddings/poet.py
openprotein_python-0.10.1.dist-info/METADATA
openprotein_python-0.10.1.dist-info/WHEEL
openprotein_python-0.10.1.dist-info/licenses/LICENSE.txt
openprotein_python-0.10.1.dist-info/RECORD
