Metadata-Version: 2.4
Name: openprotein-python
Version: 0.10.1
Summary: OpenProtein Python interface.
Author-email: Mark Gee <markgee@ne47.bio>, "Timothy Truong Jr." <ttruong@ne47.bio>, Tristan Bepler <tbepler@ne47.bio>
License-Expression: MIT
License-File: LICENSE.txt
Classifier: Development Status :: 4 - Beta
Classifier: Programming Language :: Python :: 3
Requires-Python: <3.15,>=3.10
Requires-Dist: gemmi<0.8,>=0.6.0
Requires-Dist: numpy<3,>=1.9
Requires-Dist: pandas<3,>=2.2.2
Requires-Dist: pydantic<3,>=2.5
Requires-Dist: requests<3,>=2.32.3
Requires-Dist: tomli<3,>=2.3.0
Requires-Dist: tqdm<5,>=4.66.5
